estout/__init__.py
estout/_modidx.py
estout/core.py
estout/linearmodels_results.py
estout/statsmodels_results.py
estout/utils.py
estout-0.0.5.dist-info/licenses/LICENSE
estout-0.0.5.dist-info/METADATA
estout-0.0.5.dist-info/WHEEL
estout-0.0.5.dist-info/entry_points.txt
estout-0.0.5.dist-info/top_level.txt
estout-0.0.5.dist-info/RECORD
